smartpost/__init__.py
smartpost/client.py
smartpost/errors.py
smartpost/models.py
smartpost/py.typed
smartpost/sync/__init__.py
smartpost/sync/client.py
aiosmartpost-0.3.3.dist-info/LICENSE
aiosmartpost-0.3.3.dist-info/METADATA
aiosmartpost-0.3.3.dist-info/WHEEL
aiosmartpost-0.3.3.dist-info/top_level.txt
aiosmartpost-0.3.3.dist-info/RECORD
