Metadata-Version: 2.1
Name: aiosmartpost
Version: 0.3.3
Summary: Itella SmartPost API wrapper for humans 📦
Home-page: https://github.com/HarrySky/aiosmartpost
Author: Igor Nehoroshev
Author-email: mail@neigor.me
License: Unlicense
Classifier: Development Status :: 3 - Alpha
Classifier: Intended Audience :: Developers
Classifier: Operating System :: POSIX :: Linux
Classifier: License :: OSI Approved :: The Unlicense (Unlicense)
Classifier: Programming Language :: Python :: Implementation :: CPython
Classifier: Programming Language :: Python :: 3 :: Only
Classifier: Programming Language :: Python :: 3.8
Classifier: Programming Language :: Python :: 3.9
Classifier: Topic :: Software Development :: Libraries :: Python Modules
Classifier: Typing :: Typed
Requires-Python: >=3.8
License-File: LICENSE
Requires-Dist: httpx
Requires-Dist: h2
Requires-Dist: xmltodict
